pyopenssl/__init__.py
pyopenssl/openssl.py
openssl_python-0.1.1.dist-info/LICENSE.txt
openssl_python-0.1.1.dist-info/METADATA
openssl_python-0.1.1.dist-info/WHEEL
openssl_python-0.1.1.dist-info/top_level.txt
openssl_python-0.1.1.dist-info/RECORD
