Metadata-Version: 1.1
Name: openssl-python
Version: 0.1.1
Summary: Command line interface to OpenSSL with Python3
Home-page: https://github.com/the11/openssl-python
Author: Youssef Seddik
Author-email: yseddik94@gmail.com
License: GNU GPLv3
Keywords: crypto encryption RSA-keys signature signature-verification
Platform: UNKNOWN
Classifier: Development Status :: 3 - Alpha
Classifier: Intended Audience :: Information Technology
Classifier: License :: OSI Approved :: GNU General Public License v3 (GPLv3)
Classifier: Programming Language :: Python :: 3.4
